imsciences/__init__.py
imsciences/geo.py
imsciences/mmm.py
imsciences/pull.py
imsciences/unittesting.py
imsciences/vis.py
imsciences-1.0.6.dist-info/LICENSE.txt
imsciences-1.0.6.dist-info/METADATA
imsciences-1.0.6.dist-info/PKG-INFO-TomG-HP-290722
imsciences-1.0.6.dist-info/WHEEL
imsciences-1.0.6.dist-info/top_level.txt
imsciences-1.0.6.dist-info/RECORD
