Metadata-Version: 2.1
Name: imsciences
Version: 1.0.6
Summary: IMS Data Processing Package
Author: IMS
Author-email: cam@im-sciences.com
Keywords: data processing,apis,data analysis,data visualization,machine learning
Classifier: Development Status :: 3 - Alpha
Classifier: Intended Audience :: Developers
Classifier: Programming Language :: Python :: 3
Classifier: Operating System :: Unix
Classifier: Operating System :: MacOS :: MacOS X
Classifier: Operating System :: Microsoft :: Windows
License-File: LICENSE.txt
Requires-Dist: pandas
Requires-Dist: plotly
Requires-Dist: numpy
Requires-Dist: fredapi
Requires-Dist: xgboost
Requires-Dist: scikit-learn
Requires-Dist: bs4
Requires-Dist: yfinance
Requires-Dist: holidays
Requires-Dist: google-analytics-data
Requires-Dist: geopandas
Requires-Dist: geopy
Requires-Dist: workalendar
